auto_corrector/Global_dict.txt
auto_corrector/__init__.py
auto_corrector/big.txt
auto_corrector/en_US_GB_CA_lower.txt
auto_corrector/en_US_GB_CA_mixed.txt
auto_corrector/nlp_parser.py
auto_corrector/utils.py
auto_corrector/word.py
auto_corrector/word_lists.py
auto_corrector-0.0.2.dist-info/LICENSE
auto_corrector-0.0.2.dist-info/METADATA
auto_corrector-0.0.2.dist-info/WHEEL
auto_corrector-0.0.2.dist-info/top_level.txt
auto_corrector-0.0.2.dist-info/RECORD
