Metadata-Version: 2.1
Name: auto-corrector
Version: 0.0.2
Summary: English language spelling corrector
Home-page: https://github.com/akhilkumard/auto_corrector
Author: Akhil Kumar D
Author-email: akhilkumar.doppalapudi@gmail.com
License: MIT
Keywords: Natural language spelling corrector
Platform: UNKNOWN
Classifier: Natural Language :: English
Classifier: Topic :: Text Processing :: Linguistic
Classifier: License :: OSI Approved :: MIT License
